torrent_client_cli/__init__.py
torrent_client_cli/cli.py
torrent_client_cli/torrent_client_cli.py
torrent_client_cli-0.1.0.dist-info/AUTHORS.rst
torrent_client_cli-0.1.0.dist-info/LICENSE
torrent_client_cli-0.1.0.dist-info/METADATA
torrent_client_cli-0.1.0.dist-info/WHEEL
torrent_client_cli-0.1.0.dist-info/entry_points.txt
torrent_client_cli-0.1.0.dist-info/top_level.txt
torrent_client_cli-0.1.0.dist-info/RECORD
