Metadata-Version: 2.1
Name: torrent-client-cli
Version: 0.1.0
Summary: Torrent CLI Client application
Home-page: https://github.com/subhrm/torrent_client_cli
Author: Subhendu Ranjan Mishra
Author-email: subhendu.r.mishra@hotmail.com
License: MIT license
Keywords: torrent_client_cli
Platform: UNKNOWN
Classifier: Development Status :: 2 - Pre-Alpha
Classifier: Intended Audience :: Developers
Classifier: License :: OSI Approved :: MIT License
Classifier: Natural Language :: English
Classifier: Programming Language :: Python :: 3
Classifier: Programming Language :: Python :: 3.6
Classifier: Programming Language :: Python :: 3.7
Classifier: Programming Language :: Python :: 3.8
Classifier: Programming Language :: Python :: 3.9
Classifier: Programming Language :: Python :: 3.10
Requires-Python: >=3.6
License-File: LICENSE
License-File: AUTHORS.rst
Requires-Dist: Click (>=7.0)
